<?xml version="1.0"?>
<exportedFiles>
  <exportedFile url="\Portal\SlxClient\SupportFiles\help\it\WebClient.htm" timeStamp="2012-11-29T05:22:57.0000" />
  <exportedFile url="\Portal\SlxClient\SupportFiles\help\it\WebClient.js" timeStamp="2012-11-29T05:22:57.0000" />
  <exportedFile url="\Portal\SlxClient\SupportFiles\help\it\WebClient.mcwebhelp" timeStamp="2012-11-29T05:22:57.0000" />
  <exportedFile url="\Portal\SlxClient\SupportFiles\help\it\WebClient_CSH.htm" timeStamp="2012-11-29T05:22:57.0000" />
  <exportedFile url="\Portal\SlxClient\SupportFiles\help\it\WebClient_Left.htm" timeStamp="2012-11-29T05:22:57.0000" />
  <exportedFile url="\Portal\SlxClient\SupportFiles\help\it\Content\" />
  <exportedFile url="\Portal\SlxClient\SupportFiles\help\it\Data\" />
  <exportedFile url="\Portal\SlxClient\SupportFiles\help\it\Skin\" />
</exportedFiles>