<?xml version="1.0"?>
<exportedFiles>
  <exportedFile url="\Portal\SlxClient\SupportFiles\help\de\Content\image\Accept.GIF" timeStamp="2012-11-29T05:22:35.0000" />
  <exportedFile url="\Portal\SlxClient\SupportFiles\help\de\Content\image\Accept.png" timeStamp="2012-11-29T05:22:35.0000" />
  <exportedFile url="\Portal\SlxClient\SupportFiles\help\de\Content\image\Account detail view - LAN.bmp" timeStamp="2012-11-29T05:22:35.0000" />
  <exportedFile url="\Portal\SlxClient\SupportFiles\help\de\Content\image\Account detail view - Web.bmp" timeStamp="2012-11-29T05:22:35.0000" />
  <exportedFile url="\Portal\SlxClient\SupportFiles\help\de\Content\image\Account detail view - Web.png" timeStamp="2012-11-29T05:22:35.0000" />
  <exportedFile url="\Portal\SlxClient\SupportFiles\help\de\Content\image\Account list view - LAN.bmp" timeStamp="2012-11-29T05:22:35.0000" />
  <exportedFile url="\Portal\SlxClient\SupportFiles\help\de\Content\image\Account list view - Web.bmp" timeStamp="2012-11-29T05:22:35.0000" />
  <exportedFile url="\Portal\SlxClient\SupportFiles\help\de\Content\image\Account list view.bmp" timeStamp="2012-11-29T05:22:35.0000" />
  <exportedFile url="\Portal\SlxClient\SupportFiles\help\de\Content\image\Account split view - Web.bmp" timeStamp="2012-11-29T05:22:35.0000" />
  <exportedFile url="\Portal\SlxClient\SupportFiles\help\de\Content\image\accountservice.gif" timeStamp="2012-11-29T05:22:35.0000" />
  <exportedFile url="\Portal\SlxClient\SupportFiles\help\de\Content\image\Activity Reminder.bmp" timeStamp="2012-11-29T05:22:35.0000" />
  <exportedFile url="\Portal\SlxClient\SupportFiles\help\de\Content\image\add.gif" timeStamp="2012-11-29T05:22:35.0000" />
  <exportedFile url="\Portal\SlxClient\SupportFiles\help\de\Content\image\add_custom_product.png" timeStamp="2012-11-29T05:22:35.0000" />
  <exportedFile url="\Portal\SlxClient\SupportFiles\help\de\Content\image\add_products.png" timeStamp="2012-11-29T05:22:35.0000" />
  <exportedFile url="\Portal\SlxClient\SupportFiles\help\de\Content\image\addfolder.GIF" timeStamp="2012-11-29T05:22:35.0000" />
  <exportedFile url="\Portal\SlxClient\SupportFiles\help\de\Content\image\AddGroup.PNG" timeStamp="2012-11-29T05:22:35.0000" />
  <exportedFile url="\Portal\SlxClient\SupportFiles\help\de\Content\image\additional_info_16x16.gif" timeStamp="2012-11-29T05:22:35.0000" />
  <exportedFile url="\Portal\SlxClient\SupportFiles\help\de\Content\image\addmeeting.gif" timeStamp="2012-11-29T05:22:35.0000" />
  <exportedFile url="\Portal\SlxClient\SupportFiles\help\de\Content\image\addnote.gif" timeStamp="2012-11-29T05:22:35.0000" />
  <exportedFile url="\Portal\SlxClient\SupportFiles\help\de\Content\image\addphonecall.gif" timeStamp="2012-11-29T05:22:35.0000" />
  <exportedFile url="\Portal\SlxClient\SupportFiles\help\de\Content\image\AddStage-LAN.bmp" timeStamp="2012-11-29T05:22:35.0000" />
  <exportedFile url="\Portal\SlxClient\SupportFiles\help\de\Content\image\addtodo.gif" timeStamp="2012-11-29T05:22:35.0000" />
  <exportedFile url="\Portal\SlxClient\SupportFiles\help\de\Content\image\AddTopicToFavorites.gif" timeStamp="2012-11-29T05:22:35.0000" />
  <exportedFile url="\Portal\SlxClient\SupportFiles\help\de\Content\image\AddTopicToFavorites_over.gif" timeStamp="2012-11-29T05:22:35.0000" />
  <exportedFile url="\Portal\SlxClient\SupportFiles\help\de\Content\image\AddTopicToFavorites_selected.gif" timeStamp="2012-11-29T05:22:35.0000" />
  <exportedFile url="\Portal\SlxClient\SupportFiles\help\de\Content\image\addurl.gif" timeStamp="2012-11-29T05:22:35.0000" />
  <exportedFile url="\Portal\SlxClient\SupportFiles\help\de\Content\image\AdminNav.bmp" timeStamp="2012-11-29T05:22:35.0000" />
  <exportedFile url="\Portal\SlxClient\SupportFiles\help\de\Content\image\adminonly.gif" timeStamp="2012-11-29T05:22:35.0000" />
  <exportedFile url="\Portal\SlxClient\SupportFiles\help\de\Content\image\alarm.gif" timeStamp="2012-11-29T05:22:35.0000" />
  <exportedFile url="\Portal\SlxClient\SupportFiles\help\de\Content\image\Alarm_16x16.gif" timeStamp="2012-11-29T05:22:35.0000" />
  <exportedFile url="\Portal\SlxClient\SupportFiles\help\de\Content\image\alertIcon_16x16.gif" timeStamp="2012-11-29T05:22:35.0000" />
  <exportedFile url="\Portal\SlxClient\SupportFiles\help\de\Content\image\Alerts.bmp" timeStamp="2012-11-29T05:22:35.0000" />
  <exportedFile url="\Portal\SlxClient\SupportFiles\help\de\Content\image\AlertTool.bmp" timeStamp="2012-11-29T05:22:35.0000" />
  <exportedFile url="\Portal\SlxClient\SupportFiles\help\de\Content\image\altaddr.gif" timeStamp="2012-11-29T05:22:35.0000" />
  <exportedFile url="\Portal\SlxClient\SupportFiles\help\de\Content\image\AnalysisFilterValues.bmp" timeStamp="2012-11-29T05:22:35.0000" />
  <exportedFile url="\Portal\SlxClient\SupportFiles\help\de\Content\image\AnalysisFilterValues_331x318.bmp" timeStamp="2012-11-29T05:22:35.0000" />
  <exportedFile url="\Portal\SlxClient\SupportFiles\help\de\Content\image\AnalysisView.bmp" timeStamp="2012-11-29T05:22:35.0000" />
  <exportedFile url="\Portal\SlxClient\SupportFiles\help\de\Content\image\AnalysisView_478x369.bmp" timeStamp="2012-11-29T05:22:35.0000" />
  <exportedFile url="\Portal\SlxClient\SupportFiles\help\de\Content\image\associate.gif" timeStamp="2012-11-29T05:22:35.0000" />
  <exportedFile url="\Portal\SlxClient\SupportFiles\help\de\Content\image\attach.gif" timeStamp="2012-11-29T05:22:35.0000" />
  <exportedFile url="\Portal\SlxClient\SupportFiles\help\de\Content\image\attach.png" timeStamp="2012-11-29T05:22:35.0000" />
  <exportedFile url="\Portal\SlxClient\SupportFiles\help\de\Content\image\Availability.bmp" timeStamp="2012-11-29T05:22:35.0000" />
  <exportedFile url="\Portal\SlxClient\SupportFiles\help\de\Content\image\backg.gif" timeStamp="2012-11-29T05:22:35.0000" />
  <exportedFile url="\Portal\SlxClient\SupportFiles\help\de\Content\image\BLOB.GIF" timeStamp="2012-11-29T05:22:35.0000" />
  <exportedFile url="\Portal\SlxClient\SupportFiles\help\de\Content\image\blubull.gif" timeStamp="2012-11-29T05:22:35.0000" />
  <exportedFile url="\Portal\SlxClient\SupportFiles\help\de\Content\image\calendar.gif" timeStamp="2012-11-29T05:22:35.0000" />
  <exportedFile url="\Portal\SlxClient\SupportFiles\help\de\Content\image\calendar_17x17.gif" timeStamp="2012-11-29T05:22:35.0000" />
  <exportedFile url="\Portal\SlxClient\SupportFiles\help\de\Content\image\Calendar_24x24.gif" timeStamp="2012-11-29T05:22:35.0000" />
  <exportedFile url="\Portal\SlxClient\SupportFiles\help\de\Content\image\CalendarDay.gif" timeStamp="2012-11-29T05:22:35.0000" />
  <exportedFile url="\Portal\SlxClient\SupportFiles\help\de\Content\image\CalendarMonth.gif" timeStamp="2012-11-29T05:22:35.0000" />
  <exportedFile url="\Portal\SlxClient\SupportFiles\help\de\Content\image\CalendarMoreArrow.png" timeStamp="2012-11-29T05:22:35.0000" />
  <exportedFile url="\Portal\SlxClient\SupportFiles\help\de\Content\image\CalendarWeek.gif" timeStamp="2012-11-29T05:22:35.0000" />
  <exportedFile url="\Portal\SlxClient\SupportFiles\help\de\Content\image\CalendarWorkWeek.gif" timeStamp="2012-11-29T05:22:35.0000" />
  <exportedFile url="\Portal\SlxClient\SupportFiles\help\de\Content\image\CALFIELDQUERY.GIF" timeStamp="2012-11-29T05:22:35.0000" />
  <exportedFile url="\Portal\SlxClient\SupportFiles\help\de\Content\image\cancel.png" timeStamp="2012-11-29T05:22:35.0000" />
  <exportedFile url="\Portal\SlxClient\SupportFiles\help\de\Content\image\CancelTask.gif" timeStamp="2012-11-29T05:22:35.0000" />
  <exportedFile url="\Portal\SlxClient\SupportFiles\help\de\Content\image\caution.gif" timeStamp="2012-11-29T05:22:35.0000" />
  <exportedFile url="\Portal\SlxClient\SupportFiles\help\de\Content\image\check.gif" timeStamp="2012-11-29T05:22:35.0000" />
  <exportedFile url="\Portal\SlxClient\SupportFiles\help\de\Content\image\checkbox.bmp" timeStamp="2012-11-29T05:22:35.0000" />
  <exportedFile url="\Portal\SlxClient\SupportFiles\help\de\Content\image\checkmark.GIF" timeStamp="2012-11-29T05:22:35.0000" />
  <exportedFile url="\Portal\SlxClient\SupportFiles\help\de\Content\image\close.gif" timeStamp="2012-11-29T05:22:35.0000" />
  <exportedFile url="\Portal\SlxClient\SupportFiles\help\de\Content\image\closeprintview.gif" timeStamp="2012-11-29T05:22:35.0000" />
  <exportedFile url="\Portal\SlxClient\SupportFiles\help\de\Content\image\CloseWidget.png" timeStamp="2012-11-29T05:22:35.0000" />
  <exportedFile url="\Portal\SlxClient\SupportFiles\help\de\Content\image\CloseWidget_13x13.png" timeStamp="2012-11-29T05:22:35.0000" />
  <exportedFile url="\Portal\SlxClient\SupportFiles\help\de\Content\image\collapse.gif" timeStamp="2012-11-29T05:22:35.0000" />
  <exportedFile url="\Portal\SlxClient\SupportFiles\help\de\Content\image\CollapsePane.GIF" timeStamp="2012-11-29T05:22:35.0000" />
  <exportedFile url="\Portal\SlxClient\SupportFiles\help\de\Content\image\complete.gif" timeStamp="2012-11-29T05:22:35.0000" />
  <exportedFile url="\Portal\SlxClient\SupportFiles\help\de\Content\image\CompleteTask.gif" timeStamp="2012-11-29T05:22:35.0000" />
  <exportedFile url="\Portal\SlxClient\SupportFiles\help\de\Content\image\Contact Detail-LAN.bmp" timeStamp="2012-11-29T05:22:35.0000" />
  <exportedFile url="\Portal\SlxClient\SupportFiles\help\de\Content\image\Contact Detail.bmp" timeStamp="2012-11-29T05:22:36.0000" />
  <exportedFile url="\Portal\SlxClient\SupportFiles\help\de\Content\image\copy.gif" timeStamp="2012-11-29T05:22:35.0000" />
  <exportedFile url="\Portal\SlxClient\SupportFiles\help\de\Content\image\CopyContact_16x16.png" timeStamp="2012-11-29T05:22:35.0000" />
  <exportedFile url="\Portal\SlxClient\SupportFiles\help\de\Content\image\Copyrecord.gif" timeStamp="2012-11-29T05:22:35.0000" />
  <exportedFile url="\Portal\SlxClient\SupportFiles\help\de\Content\image\Dashboard-Web.bmp" timeStamp="2012-11-29T05:22:36.0000" />
  <exportedFile url="\Portal\SlxClient\SupportFiles\help\de\Content\image\datestamp.gif" timeStamp="2012-11-29T05:22:35.0000" />
  <exportedFile url="\Portal\SlxClient\SupportFiles\help\de\Content\image\DATETIME.GIF" timeStamp="2012-11-29T05:22:35.0000" />
  <exportedFile url="\Portal\SlxClient\SupportFiles\help\de\Content\image\dbchange.gif" timeStamp="2012-11-29T05:22:35.0000" />
  <exportedFile url="\Portal\SlxClient\SupportFiles\help\de\Content\image\Decline.png" timeStamp="2012-11-29T05:22:35.0000" />
  <exportedFile url="\Portal\SlxClient\SupportFiles\help\de\Content\image\Delete Mouse Over Green Gradient.gif" timeStamp="2012-11-29T05:22:35.0000" />
  <exportedFile url="\Portal\SlxClient\SupportFiles\help\de\Content\image\Delete Selected Green Gradient.gif" timeStamp="2012-11-29T05:22:35.0000" />
  <exportedFile url="\Portal\SlxClient\SupportFiles\help\de\Content\image\Delete.gif" timeStamp="2012-11-29T05:22:35.0000" />
  <exportedFile url="\Portal\SlxClient\SupportFiles\help\de\Content\image\deletefolder.GIF" timeStamp="2012-11-29T05:22:35.0000" />
  <exportedFile url="\Portal\SlxClient\SupportFiles\help\de\Content\image\dialog.gif" timeStamp="2012-11-29T05:22:35.0000" />
  <exportedFile url="\Portal\SlxClient\SupportFiles\help\de\Content\image\Dismiss_16x16.ico" timeStamp="2012-11-29T05:22:35.0000" />
  <exportedFile url="\Portal\SlxClient\SupportFiles\help\de\Content\image\Dismiss_16x16.png" timeStamp="2012-11-29T05:22:36.0000" />
  <exportedFile url="\Portal\SlxClient\SupportFiles\help\de\Content\image\dropcurs.gif" timeStamp="2012-11-29T05:22:35.0000" />
  <exportedFile url="\Portal\SlxClient\SupportFiles\help\de\Content\image\DropDownClosed.gif" timeStamp="2012-11-29T05:22:36.0000" />
  <exportedFile url="\Portal\SlxClient\SupportFiles\help\de\Content\image\DropDownOpen.gif" timeStamp="2012-11-29T05:22:36.0000" />
  <exportedFile url="\Portal\SlxClient\SupportFiles\help\de\Content\image\edit.gif" timeStamp="2012-11-29T05:22:35.0000" />
  <exportedFile url="\Portal\SlxClient\SupportFiles\help\de\Content\image\Edit_Widget_12x12.png" timeStamp="2012-11-29T05:22:36.0000" />
  <exportedFile url="\Portal\SlxClient\SupportFiles\help\de\Content\image\editfolder.GIF" timeStamp="2012-11-29T05:22:36.0000" />
  <exportedFile url="\Portal\SlxClient\SupportFiles\help\de\Content\image\editwidget.gif" timeStamp="2012-11-29T05:22:36.0000" />
  <exportedFile url="\Portal\SlxClient\SupportFiles\help\de\Content\image\ellipses.gif" timeStamp="2012-11-29T05:22:36.0000" />
  <exportedFile url="\Portal\SlxClient\SupportFiles\help\de\Content\image\email.gif" timeStamp="2012-11-29T05:22:36.0000" />
  <exportedFile url="\Portal\SlxClient\SupportFiles\help\de\Content\image\ESP.gif" timeStamp="2012-11-29T05:22:36.0000" />
  <exportedFile url="\Portal\SlxClient\SupportFiles\help\de\Content\image\event.gif" timeStamp="2012-11-29T05:22:36.0000" />
  <exportedFile url="\Portal\SlxClient\SupportFiles\help\de\Content\image\expand.gif" timeStamp="2012-11-29T05:22:36.0000" />
  <exportedFile url="\Portal\SlxClient\SupportFiles\help\de\Content\image\ExpandClosed.gif" timeStamp="2012-11-29T05:22:36.0000" />
  <exportedFile url="\Portal\SlxClient\SupportFiles\help\de\Content\image\expandfilter.JPG" timeStamp="2012-11-29T05:22:36.0000" />
  <exportedFile url="\Portal\SlxClient\SupportFiles\help\de\Content\image\ExpandOpen.gif" timeStamp="2012-11-29T05:22:36.0000" />
  <exportedFile url="\Portal\SlxClient\SupportFiles\help\de\Content\image\ExpandPane.GIF" timeStamp="2012-11-29T05:22:36.0000" />
  <exportedFile url="\Portal\SlxClient\SupportFiles\help\de\Content\image\Fax.gif" timeStamp="2012-11-29T05:22:36.0000" />
  <exportedFile url="\Portal\SlxClient\SupportFiles\help\de\Content\image\filteraddremove.JPG" timeStamp="2012-11-29T05:22:36.0000" />
  <exportedFile url="\Portal\SlxClient\SupportFiles\help\de\Content\image\filterapply.JPG" timeStamp="2012-11-29T05:22:36.0000" />
  <exportedFile url="\Portal\SlxClient\SupportFiles\help\de\Content\image\filtercriterialist.JPG" timeStamp="2012-11-29T05:22:36.0000" />
  <exportedFile url="\Portal\SlxClient\SupportFiles\help\de\Content\image\filterheading.JPG" timeStamp="2012-11-29T05:22:36.0000" />
  <exportedFile url="\Portal\SlxClient\SupportFiles\help\de\Content\image\filternotehist.gif" timeStamp="2012-11-29T05:22:36.0000" />
  <exportedFile url="\Portal\SlxClient\SupportFiles\help\de\Content\image\find.gif" timeStamp="2012-11-29T05:22:36.0000" />
  <exportedFile url="\Portal\SlxClient\SupportFiles\help\de\Content\image\first.gif" timeStamp="2012-11-29T05:22:36.0000" />
  <exportedFile url="\Portal\SlxClient\SupportFiles\help\de\Content\image\FIXED.GIF" timeStamp="2012-11-29T05:22:36.0000" />
  <exportedFile url="\Portal\SlxClient\SupportFiles\help\de\Content\image\form_manager.png" timeStamp="2012-11-29T05:22:36.0000" />
  <exportedFile url="\Portal\SlxClient\SupportFiles\help\de\Content\image\Google_16x16.gif" timeStamp="2012-11-29T05:22:36.0000" />
  <exportedFile url="\Portal\SlxClient\SupportFiles\help\de\Content\image\grayClearCloseIcon.png" timeStamp="2012-11-29T05:22:36.0000" />
  <exportedFile url="\Portal\SlxClient\SupportFiles\help\de\Content\image\Group is in Client Side Mode.gif" timeStamp="2012-11-29T05:22:36.0000" />
  <exportedFile url="\Portal\SlxClient\SupportFiles\help\de\Content\image\Group is in Virtual Server Mode.gif" timeStamp="2012-11-29T05:22:36.0000" />
  <exportedFile url="\Portal\SlxClient\SupportFiles\help\de\Content\image\Groups.bmp" timeStamp="2012-11-29T05:22:36.0000" />
  <exportedFile url="\Portal\SlxClient\SupportFiles\help\de\Content\image\groupsArrow.png" timeStamp="2012-11-29T05:22:36.0000" />
  <exportedFile url="\Portal\SlxClient\SupportFiles\help\de\Content\image\hand.JPG" timeStamp="2012-11-29T05:22:36.0000" />
  <exportedFile url="\Portal\SlxClient\SupportFiles\help\de\Content\image\help.gif" timeStamp="2012-11-29T05:22:36.0000" />
  <exportedFile url="\Portal\SlxClient\SupportFiles\help\de\Content\image\help.png" timeStamp="2012-11-29T05:22:36.0000" />
  <exportedFile url="\Portal\SlxClient\SupportFiles\help\de\Content\image\Import Lead 1 -Web.bmp" timeStamp="2012-11-29T05:22:36.0000" />
  <exportedFile url="\Portal\SlxClient\SupportFiles\help\de\Content\image\ImportHistory.gif" timeStamp="2012-11-29T05:22:36.0000" />
  <exportedFile url="\Portal\SlxClient\SupportFiles\help\de\Content\image\ImportLeadPreview-LAN.bmp" timeStamp="2012-11-29T05:22:36.0000" />
  <exportedFile url="\Portal\SlxClient\SupportFiles\help\de\Content\image\ImportLeads-LAN.bmp" timeStamp="2012-11-29T05:22:36.0000" />
  <exportedFile url="\Portal\SlxClient\SupportFiles\help\de\Content\image\ImportLeads.gif" timeStamp="2012-11-29T05:22:36.0000" />
  <exportedFile url="\Portal\SlxClient\SupportFiles\help\de\Content\image\Insert Defect- LAN.bmp" timeStamp="2012-11-29T05:22:36.0000" />
  <exportedFile url="\Portal\SlxClient\SupportFiles\help\de\Content\image\Insert Defect- Web.bmp" timeStamp="2012-11-29T05:22:36.0000" />
  <exportedFile url="\Portal\SlxClient\SupportFiles\help\de\Content\image\InsertLead-LAN.bmp" timeStamp="2012-11-29T05:22:36.0000" />
  <exportedFile url="\Portal\SlxClient\SupportFiles\help\de\Content\image\InsertLead-Web.bmp" timeStamp="2012-11-29T05:22:36.0000" />
  <exportedFile url="\Portal\SlxClient\SupportFiles\help\de\Content\image\InsertNewContract-LAN.bmp" timeStamp="2012-11-29T05:22:36.0000" />
  <exportedFile url="\Portal\SlxClient\SupportFiles\help\de\Content\image\InsertNewTicket-LAN.bmp" timeStamp="2012-11-29T05:22:36.0000" />
  <exportedFile url="\Portal\SlxClient\SupportFiles\help\de\Content\image\InsertNewTicket-Web.bmp" timeStamp="2012-11-29T05:22:36.0000" />
  <exportedFile url="\Portal\SlxClient\SupportFiles\help\de\Content\image\INTEGER.GIF" timeStamp="2012-11-29T05:22:36.0000" />
  <exportedFile url="\Portal\SlxClient\SupportFiles\help\de\Content\image\JOIN.GIF" timeStamp="2012-11-29T05:22:36.0000" />
  <exportedFile url="\Portal\SlxClient\SupportFiles\help\de\Content\image\JOINDISSECT.GIF" timeStamp="2012-11-29T05:22:36.0000" />
  <exportedFile url="\Portal\SlxClient\SupportFiles\help\de\Content\image\LandingMenu.gif" timeStamp="2012-11-29T05:22:36.0000" />
  <exportedFile url="\Portal\SlxClient\SupportFiles\help\de\Content\image\LandingRefresh.GIF" timeStamp="2012-11-29T05:22:36.0000" />
  <exportedFile url="\Portal\SlxClient\SupportFiles\help\de\Content\image\LandingRemove.gif" timeStamp="2012-11-29T05:22:36.0000" />
  <exportedFile url="\Portal\SlxClient\SupportFiles\help\de\Content\image\last.gif" timeStamp="2012-11-29T05:22:36.0000" />
  <exportedFile url="\Portal\SlxClient\SupportFiles\help\de\Content\image\letter.gif" timeStamp="2012-11-29T05:22:36.0000" />
  <exportedFile url="\Portal\SlxClient\SupportFiles\help\de\Content\image\list view.gif" timeStamp="2012-11-29T05:22:36.0000" />
  <exportedFile url="\Portal\SlxClient\SupportFiles\help\de\Content\image\LitRequest.gif" timeStamp="2012-11-29T05:22:36.0000" />
  <exportedFile url="\Portal\SlxClient\SupportFiles\help\de\Content\image\lock_all_16x16.png" timeStamp="2012-11-29T05:22:36.0000" />
  <exportedFile url="\Portal\SlxClient\SupportFiles\help\de\Content\image\Login Screen.bmp" timeStamp="2012-11-29T05:22:36.0000" />
  <exportedFile url="\Portal\SlxClient\SupportFiles\help\de\Content\image\Login ScreenWeb.bmp" timeStamp="2012-11-29T05:22:36.0000" />
  <exportedFile url="\Portal\SlxClient\SupportFiles\help\de\Content\image\macro1_wmf.gif" timeStamp="2012-11-29T05:22:36.0000" />
  <exportedFile url="\Portal\SlxClient\SupportFiles\help\de\Content\image\macro2_wmf.gif" timeStamp="2012-11-29T05:22:36.0000" />
  <exportedFile url="\Portal\SlxClient\SupportFiles\help\de\Content\image\mail.gif" timeStamp="2012-11-29T05:22:36.0000" />
  <exportedFile url="\Portal\SlxClient\SupportFiles\help\de\Content\image\Manytomany.gif" timeStamp="2012-11-29T05:22:36.0000" />
  <exportedFile url="\Portal\SlxClient\SupportFiles\help\de\Content\image\map1.gif" timeStamp="2012-11-29T05:22:36.0000" />
  <exportedFile url="\Portal\SlxClient\SupportFiles\help\de\Content\image\MarketingNav.bmp" timeStamp="2012-11-29T05:22:36.0000" />
  <exportedFile url="\Portal\SlxClient\SupportFiles\help\de\Content\image\Maximize.gif" timeStamp="2012-11-29T05:22:36.0000" />
  <exportedFile url="\Portal\SlxClient\SupportFiles\help\de\Content\image\meetcalglyph.gif" timeStamp="2012-11-29T05:22:36.0000" />
  <exportedFile url="\Portal\SlxClient\SupportFiles\help\de\Content\image\meeting.gif" timeStamp="2012-11-29T05:22:36.0000" />
  <exportedFile url="\Portal\SlxClient\SupportFiles\help\de\Content\image\Meeting_16x16.gif" timeStamp="2012-11-29T05:22:36.0000" />
  <exportedFile url="\Portal\SlxClient\SupportFiles\help\de\Content\image\Midimize.gif" timeStamp="2012-11-29T05:22:36.0000" />
  <exportedFile url="\Portal\SlxClient\SupportFiles\help\de\Content\image\miniimize widget.GIF" timeStamp="2012-11-29T05:22:36.0000" />
  <exportedFile url="\Portal\SlxClient\SupportFiles\help\de\Content\image\miniimize widget_13x13.gif" timeStamp="2012-11-29T05:22:36.0000" />
  <exportedFile url="\Portal\SlxClient\SupportFiles\help\de\Content\image\Minimize.gif" timeStamp="2012-11-29T05:22:36.0000" />
  <exportedFile url="\Portal\SlxClient\SupportFiles\help\de\Content\image\minus.gif" timeStamp="2012-11-29T05:22:36.0000" />
  <exportedFile url="\Portal\SlxClient\SupportFiles\help\de\Content\image\move.gif" timeStamp="2012-11-29T05:22:36.0000" />
  <exportedFile url="\Portal\SlxClient\SupportFiles\help\de\Content\image\MovePointer.gif" timeStamp="2012-11-29T05:22:36.0000" />
  <exportedFile url="\Portal\SlxClient\SupportFiles\help\de\Content\image\multiopps.gif" timeStamp="2012-11-29T05:22:36.0000" />
  <exportedFile url="\Portal\SlxClient\SupportFiles\help\de\Content\image\NavBarGroupButtons.bmp" timeStamp="2012-11-29T05:22:36.0000" />
  <exportedFile url="\Portal\SlxClient\SupportFiles\help\de\Content\image\NavGroup buttons.bmp" timeStamp="2012-11-29T05:22:36.0000" />
  <exportedFile url="\Portal\SlxClient\SupportFiles\help\de\Content\image\NewCompany.gif" timeStamp="2012-11-29T05:22:36.0000" />
  <exportedFile url="\Portal\SlxClient\SupportFiles\help\de\Content\image\Next Mouse Over.gif" timeStamp="2012-11-29T05:22:36.0000" />
  <exportedFile url="\Portal\SlxClient\SupportFiles\help\de\Content\image\Next Selected.gif" timeStamp="2012-11-29T05:22:36.0000" />
  <exportedFile url="\Portal\SlxClient\SupportFiles\help\de\Content\image\nextg.gif" timeStamp="2012-11-29T05:22:36.0000" />
  <exportedFile url="\Portal\SlxClient\SupportFiles\help\de\Content\image\note.gif" timeStamp="2012-11-29T05:22:36.0000" />
  <exportedFile url="\Portal\SlxClient\SupportFiles\help\de\Content\image\notes.gif" timeStamp="2012-11-29T05:22:36.0000" />
  <exportedFile url="\Portal\SlxClient\SupportFiles\help\de\Content\image\ONETOMANY.GIF" timeStamp="2012-11-29T05:22:36.0000" />
  <exportedFile url="\Portal\SlxClient\SupportFiles\help\de\Content\image\ONETOONE.GIF" timeStamp="2012-11-29T05:22:36.0000" />
  <exportedFile url="\Portal\SlxClient\SupportFiles\help\de\Content\image\Opp Stats.bmp" timeStamp="2012-11-29T05:22:36.0000" />
  <exportedFile url="\Portal\SlxClient\SupportFiles\help\de\Content\image\oppdashboard.gif" timeStamp="2012-11-29T05:22:36.0000" />
  <exportedFile url="\Portal\SlxClient\SupportFiles\help\de\Content\image\Opportunity Detail-LAN.bmp" timeStamp="2012-11-29T05:22:36.0000" />
  <exportedFile url="\Portal\SlxClient\SupportFiles\help\de\Content\image\Opportunity Detail-Web - Copy.bmp" timeStamp="2012-11-29T05:22:36.0000" />
  <exportedFile url="\Portal\SlxClient\SupportFiles\help\de\Content\image\Opportunity Detail-Web.bmp" timeStamp="2012-11-29T05:22:36.0000" />
  <exportedFile url="\Portal\SlxClient\SupportFiles\help\de\Content\image\opportunity.gif" timeStamp="2012-11-29T05:22:36.0000" />
  <exportedFile url="\Portal\SlxClient\SupportFiles\help\de\Content\image\OpportunityStatistics-LAN.bmp" timeStamp="2012-11-29T05:22:36.0000" />
  <exportedFile url="\Portal\SlxClient\SupportFiles\help\de\Content\image\options_12x12.png" timeStamp="2012-11-29T05:22:36.0000" />
  <exportedFile url="\Portal\SlxClient\SupportFiles\help\de\Content\image\OriginalOrganic.bmp" timeStamp="2012-11-29T05:22:36.0000" />
  <exportedFile url="\Portal\SlxClient\SupportFiles\help\de\Content\image\Padlock.gif" timeStamp="2012-11-29T05:22:36.0000" />
  <exportedFile url="\Portal\SlxClient\SupportFiles\help\de\Content\image\Padlock_27x26.gif" timeStamp="2012-11-29T05:22:36.0000" />
  <exportedFile url="\Portal\SlxClient\SupportFiles\help\de\Content\image\PastDueTool.bmp" timeStamp="2012-11-29T05:22:36.0000" />
  <exportedFile url="\Portal\SlxClient\SupportFiles\help\de\Content\image\personal.gif" timeStamp="2012-11-29T05:22:36.0000" />
  <exportedFile url="\Portal\SlxClient\SupportFiles\help\de\Content\image\personalactivity.gif" timeStamp="2012-11-29T05:22:36.0000" />
  <exportedFile url="\Portal\SlxClient\SupportFiles\help\de\Content\image\personcalglyph.gif" timeStamp="2012-11-29T05:22:36.0000" />
  <exportedFile url="\Portal\SlxClient\SupportFiles\help\de\Content\image\phonecalglyph.gif" timeStamp="2012-11-29T05:22:36.0000" />
  <exportedFile url="\Portal\SlxClient\SupportFiles\help\de\Content\image\phonecall.gif" timeStamp="2012-11-29T05:22:36.0000" />
  <exportedFile url="\Portal\SlxClient\SupportFiles\help\de\Content\image\PhoneCall_16x16.gif" timeStamp="2012-11-29T05:22:36.0000" />
  <exportedFile url="\Portal\SlxClient\SupportFiles\help\de\Content\image\plus.gif" timeStamp="2012-11-29T05:22:36.0000" />
  <exportedFile url="\Portal\SlxClient\SupportFiles\help\de\Content\image\Previous Mouse Over.gif" timeStamp="2012-11-29T05:22:36.0000" />
  <exportedFile url="\Portal\SlxClient\SupportFiles\help\de\Content\image\Previous Selected.gif" timeStamp="2012-11-29T05:22:36.0000" />
  <exportedFile url="\Portal\SlxClient\SupportFiles\help\de\Content\image\PrevNextButtons.bmp" timeStamp="2012-11-29T05:22:36.0000" />
  <exportedFile url="\Portal\SlxClient\SupportFiles\help\de\Content\image\printview.gif" timeStamp="2012-11-29T05:22:36.0000" />
  <exportedFile url="\Portal\SlxClient\SupportFiles\help\de\Content\image\procarrowblk.gif" timeStamp="2012-11-29T05:22:36.0000" />
  <exportedFile url="\Portal\SlxClient\SupportFiles\help\de\Content\image\procdialogerr.gif" timeStamp="2012-11-29T05:22:36.0000" />
  <exportedFile url="\Portal\SlxClient\SupportFiles\help\de\Content\image\procdialogexcl.gif" timeStamp="2012-11-29T05:22:36.0000" />
  <exportedFile url="\Portal\SlxClient\SupportFiles\help\de\Content\image\procdialoginfo.gif" timeStamp="2012-11-29T05:22:36.0000" />
  <exportedFile url="\Portal\SlxClient\SupportFiles\help\de\Content\image\procdialogquest.gif" timeStamp="2012-11-29T05:22:36.0000" />
  <exportedFile url="\Portal\SlxClient\SupportFiles\help\de\Content\image\process.gif" timeStamp="2012-11-29T05:22:36.0000" />
  <exportedFile url="\Portal\SlxClient\SupportFiles\help\de\Content\image\procomplete.gif" timeStamp="2012-11-29T05:22:36.0000" />
  <exportedFile url="\Portal\SlxClient\SupportFiles\help\de\Content\image\PromoteAccount.gif" timeStamp="2012-11-29T05:22:36.0000" />
  <exportedFile url="\Portal\SlxClient\SupportFiles\help\de\Content\image\punchin.gif" timeStamp="2012-11-29T05:22:36.0000" />
  <exportedFile url="\Portal\SlxClient\SupportFiles\help\de\Content\image\QBGROUPEXAMPLE.gif" timeStamp="2012-11-29T05:22:36.0000" />
  <exportedFile url="\Portal\SlxClient\SupportFiles\help\de\Content\image\question.gif" timeStamp="2012-11-29T05:22:36.0000" />
  <exportedFile url="\Portal\SlxClient\SupportFiles\help\de\Content\image\Record_SLX.gif" timeStamp="2012-11-29T05:22:36.0000" />
  <exportedFile url="\Portal\SlxClient\SupportFiles\help\de\Content\image\recurring.png" timeStamp="2012-11-29T05:22:36.0000" />
  <exportedFile url="\Portal\SlxClient\SupportFiles\help\de\Content\image\refresh.png" timeStamp="2012-11-29T05:22:36.0000" />
  <exportedFile url="\Portal\SlxClient\SupportFiles\help\de\Content\image\refreshnew.gif" timeStamp="2012-11-29T05:22:36.0000" />
  <exportedFile url="\Portal\SlxClient\SupportFiles\help\de\Content\image\remotes.gif" timeStamp="2012-11-29T05:22:36.0000" />
  <exportedFile url="\Portal\SlxClient\SupportFiles\help\de\Content\image\renumber.gif" timeStamp="2012-11-29T05:22:36.0000" />
  <exportedFile url="\Portal\SlxClient\SupportFiles\help\de\Content\image\Report.gif" timeStamp="2012-11-29T05:22:36.0000" />
  <exportedFile url="\Portal\SlxClient\SupportFiles\help\de\Content\image\rescheduleactivity.gif" timeStamp="2012-11-29T05:22:36.0000" />
  <exportedFile url="\Portal\SlxClient\SupportFiles\help\de\Content\image\reset.gif" timeStamp="2012-11-29T05:22:36.0000" />
  <exportedFile url="\Portal\SlxClient\SupportFiles\help\de\Content\image\Result Used.gif" timeStamp="2012-11-29T05:22:36.0000" />
  <exportedFile url="\Portal\SlxClient\SupportFiles\help\de\Content\image\ReturnDetail-LAN.bmp" timeStamp="2012-11-29T05:22:36.0000" />
  <exportedFile url="\Portal\SlxClient\SupportFiles\help\de\Content\image\ReturnDetail-Web.bmp" timeStamp="2012-11-29T05:22:36.0000" />
  <exportedFile url="\Portal\SlxClient\SupportFiles\help\de\Content\image\Rollover.gif" timeStamp="2012-11-29T05:22:36.0000" />
  <exportedFile url="\Portal\SlxClient\SupportFiles\help\de\Content\image\sage-graphic---lines6.jpg" timeStamp="2012-11-29T05:22:36.0000" />
  <exportedFile url="\Portal\SlxClient\SupportFiles\help\de\Content\image\SalesDashboard.bmp" timeStamp="2012-11-29T05:22:36.0000" />
  <exportedFile url="\Portal\SlxClient\SupportFiles\help\de\Content\image\SalesDashboard_785x498.bmp" timeStamp="2012-11-29T05:22:36.0000" />
  <exportedFile url="\Portal\SlxClient\SupportFiles\help\de\Content\image\SalesNav.bmp" timeStamp="2012-11-29T05:22:36.0000" />
  <exportedFile url="\Portal\SlxClient\SupportFiles\help\de\Content\image\saveclear.gif" timeStamp="2012-11-29T05:22:36.0000" />
  <exportedFile url="\Portal\SlxClient\SupportFiles\help\de\Content\image\savenew.gif" timeStamp="2012-11-29T05:22:36.0000" />
  <exportedFile url="\Portal\SlxClient\SupportFiles\help\de\Content\image\Script.gif" timeStamp="2012-11-29T05:22:36.0000" />
  <exportedFile url="\Portal\SlxClient\SupportFiles\help\de\Content\image\securityManager_16x16.png" timeStamp="2012-11-29T05:22:36.0000" />
  <exportedFile url="\Portal\SlxClient\SupportFiles\help\de\Content\image\SendWord.gif" timeStamp="2012-11-29T05:22:36.0000" />
  <exportedFile url="\Portal\SlxClient\SupportFiles\help\de\Content\image\ServiceNav.bmp" timeStamp="2012-11-29T05:22:36.0000" />
  <exportedFile url="\Portal\SlxClient\SupportFiles\help\de\Content\image\settings.gif" timeStamp="2012-11-29T05:22:36.0000" />
  <exportedFile url="\Portal\SlxClient\SupportFiles\help\de\Content\image\SLXDeskMgr.gif" timeStamp="2012-11-29T05:22:36.0000" />
  <exportedFile url="\Portal\SlxClient\SupportFiles\help\de\Content\image\Slxlogo.gif" timeStamp="2012-11-29T05:22:36.0000" />
  <exportedFile url="\Portal\SlxClient\SupportFiles\help\de\Content\image\smGreenArrowClosed.png" timeStamp="2012-11-29T05:22:36.0000" />
  <exportedFile url="\Portal\SlxClient\SupportFiles\help\de\Content\image\smGreenArrowOpen.png" timeStamp="2012-11-29T05:22:36.0000" />
  <exportedFile url="\Portal\SlxClient\SupportFiles\help\de\Content\image\SnoozeAlarm_16x16.png" timeStamp="2012-11-29T05:22:36.0000" />
  <exportedFile url="\Portal\SlxClient\SupportFiles\help\de\Content\image\SpeedSearch.gif" timeStamp="2012-11-29T05:22:36.0000" />
  <exportedFile url="\Portal\SlxClient\SupportFiles\help\de\Content\image\Speedsearcharrows.gif" timeStamp="2012-11-29T05:22:36.0000" />
  <exportedFile url="\Portal\SlxClient\SupportFiles\help\de\Content\image\StandardProblem.png" timeStamp="2012-11-29T05:22:36.0000" />
  <exportedFile url="\Portal\SlxClient\SupportFiles\help\de\Content\image\StandardResolution.png" timeStamp="2012-11-29T05:22:36.0000" />
  <exportedFile url="\Portal\SlxClient\SupportFiles\help\de\Content\image\Stop.gif" timeStamp="2012-11-29T05:22:36.0000" />
  <exportedFile url="\Portal\SlxClient\SupportFiles\help\de\Content\image\STRING.GIF" timeStamp="2012-11-29T05:22:36.0000" />
  <exportedFile url="\Portal\SlxClient\SupportFiles\help\de\Content\image\SubProcess.gif" timeStamp="2012-11-29T05:22:36.0000" />
  <exportedFile url="\Portal\SlxClient\SupportFiles\help\de\Content\image\SupportNav.bmp" timeStamp="2012-11-29T05:22:36.0000" />
  <exportedFile url="\Portal\SlxClient\SupportFiles\help\de\Content\image\Task_List_3D_24x24.gif" timeStamp="2012-11-29T05:22:36.0000" />
  <exportedFile url="\Portal\SlxClient\SupportFiles\help\de\Content\image\ticket.gif" timeStamp="2012-11-29T05:22:36.0000" />
  <exportedFile url="\Portal\SlxClient\SupportFiles\help\de\Content\image\ticketactivity.gif" timeStamp="2012-11-29T05:22:36.0000" />
  <exportedFile url="\Portal\SlxClient\SupportFiles\help\de\Content\image\To_Do_16x16.gif" timeStamp="2012-11-29T05:22:36.0000" />
  <exportedFile url="\Portal\SlxClient\SupportFiles\help\de\Content\image\todo.gif" timeStamp="2012-11-29T05:22:36.0000" />
  <exportedFile url="\Portal\SlxClient\SupportFiles\help\de\Content\image\todocalglyph.gif" timeStamp="2012-11-29T05:22:36.0000" />
  <exportedFile url="\Portal\SlxClient\SupportFiles\help\de\Content\image\TomDaleDetail.bmp" timeStamp="2012-11-29T05:22:36.0000" />
  <exportedFile url="\Portal\SlxClient\SupportFiles\help\de\Content\image\unconfirmedActivity.png" timeStamp="2012-11-29T05:22:36.0000" />
  <exportedFile url="\Portal\SlxClient\SupportFiles\help\de\Content\image\undo.png" timeStamp="2012-11-29T05:22:36.0000" />
  <exportedFile url="\Portal\SlxClient\SupportFiles\help\de\Content\image\unlock_all_16x16.png" timeStamp="2012-11-29T05:22:36.0000" />
  <exportedFile url="\Portal\SlxClient\SupportFiles\help\de\Content\image\update.gif" timeStamp="2012-11-29T05:22:36.0000" />
  <exportedFile url="\Portal\SlxClient\SupportFiles\help\de\Content\image\updatetarget.gif" timeStamp="2012-11-29T05:22:36.0000" />
  <exportedFile url="\Portal\SlxClient\SupportFiles\help\de\Content\image\View.gif" timeStamp="2012-11-29T05:22:36.0000" />
  <exportedFile url="\Portal\SlxClient\SupportFiles\help\de\Content\image\web.gif" timeStamp="2012-11-29T05:22:36.0000" />
  <exportedFile url="\Portal\SlxClient\SupportFiles\help\de\Content\image\welcome_24x24.gif" timeStamp="2012-11-29T05:22:36.0000" />
  <exportedFile url="\Portal\SlxClient\SupportFiles\help\de\Content\image\Workspace- LAN.bmp" timeStamp="2012-11-29T05:22:36.0000" />
  <exportedFile url="\Portal\SlxClient\SupportFiles\help\de\Content\image\Workspace- Web.bmp" timeStamp="2012-11-29T05:22:36.0000" />
  <exportedFile url="\Portal\SlxClient\SupportFiles\help\de\Content\image\Workspace- Web1.bmp" timeStamp="2012-11-29T05:22:36.0000" />
  <exportedFile url="\Portal\SlxClient\SupportFiles\help\de\Content\image\Workspace.bmp" timeStamp="2012-11-29T05:22:36.0000" />
  <exportedFile url="\Portal\SlxClient\SupportFiles\help\de\Content\image\www.gif" timeStamp="2012-11-29T05:22:36.0000" />
  <exportedFile url="\Portal\SlxClient\SupportFiles\help\de\Content\image\ZEROTOMANY.GIF" timeStamp="2012-11-29T05:22:36.0000" />
  <exportedFile url="\Portal\SlxClient\SupportFiles\help\de\Content\image\ZEROTOONE.GIF" timeStamp="2012-11-29T05:22:36.0000" />
</exportedFiles>